pdb_modifier/__init__.py
pdb_modifier/modify.py
pdb_modifier-0.1.0.dist-info/METADATA
pdb_modifier-0.1.0.dist-info/WHEEL
pdb_modifier-0.1.0.dist-info/entry_points.txt
pdb_modifier-0.1.0.dist-info/top_level.txt
pdb_modifier-0.1.0.dist-info/RECORD
